CHANGES.rst
LICENSE
MANIFEST.in
README.rst
setup.py
SQLAlchemy_Sluggable.egg-info/PKG-INFO
SQLAlchemy_Sluggable.egg-info/SOURCES.txt
SQLAlchemy_Sluggable.egg-info/dependency_links.txt
SQLAlchemy_Sluggable.egg-info/not-zip-safe
SQLAlchemy_Sluggable.egg-info/requires.txt
SQLAlchemy_Sluggable.egg-info/top_level.txt
sqlalchemy_sluggable/__init__.py