Metadata-Version: 1.1
Name: SQLAlchemy-Sluggable
Version: 0.1.1
Summary: Configurable slugs to SQLAlchemy models.
Home-page: https://github.com/kvesteri/sqlalchemy-sluggable
Author: Janne Vanhala, Konsta Vesterinen
Author-email: janne@fastmonkeys.com, konsta@fastmonkeys.com
License: BSD
Platform: any
Classifier: Environment :: Web Environment
Classifier: Intended Audience :: Developers
Classifier: License :: OSI Approved :: BSD License
Classifier: Operating System :: OS Independent
Classifier: Programming Language :: Python
Classifier: Topic :: Internet :: WWW/HTTP :: Dynamic Content
Classifier: Topic :: Software Development :: Libraries :: Python Modules
